empowered/__init__.py
empowered/logger_setup.py
empowered/main.py
empowered/utils.py
empowered-0.1.2.dist-info/licenses/LICENSE
empowered-0.1.2.dist-info/METADATA
empowered-0.1.2.dist-info/WHEEL
empowered-0.1.2.dist-info/top_level.txt
empowered-0.1.2.dist-info/RECORD
