Metadata-Version: 2.4
Name: empowered
Version: 0.1.2
Summary: EmpowerEd project utilities and API
Author: Na'Sir Miller
License-File: LICENSE
Dynamic: license-file
